{
  "project_info": {
    "project_number": "811716426743",
    "project_id": "kiva-d24b6",
    "storage_bucket": "kiva-d24b6.firebasestorage.app"
  },
  "client": [
    {
      "client_info": {
        "mobilesdk_app_id": "1:811716426743:android:094d73f912a596dee44cf2",
        "android_client_info": {
          "package_name": "com.example.kiva"
        }
      },
      "oauth_client": [],
      "api_key": [
        {
          "current_key": "AIzaSyDX_f4F3ajarhsHn5uj9jR27n31DaxVEE0"
        }
      ],
      "services": {
        "appinvite_service": {
          "other_platform_oauth_client": []
        }
      }
    }
  ],
  "configuration_version": "1"
}